TitanicAttempt
