Metadata-Version: 1.1
Name: titanic
Version: 4.1
Summary: Practice ML & travis/coveralls with titanic data set
Home-page: https://github.com/brookemosby/titanic
Author: Brooke V Mosby
Author-email: brooke.mosby.byu@gmail.com
License: MIT
Platform: UNKNOWN
Classifier: Development Status :: 2 - Pre-Alpha
Classifier: Intended Audience :: Other Audience
Classifier: Natural Language :: English
Classifier: Operating System :: MacOS
Classifier: Operating System :: Microsoft :: Windows
Classifier: Programming Language :: Python
Classifier: Programming Language :: Python :: 2
Classifier: Programming Language :: Python :: 2.7
Classifier: Programming Language :: Python :: 3
Classifier: Programming Language :: Python :: 3.5
